{
  "id": "cloudflare-backend-foundation",
  "name": "cloudflare-backend-foundation",
  "title": "cloudflare backend foundation",
  "description": "",
  "status": "completed",
  "dev_type": null,
  "scope": null,
  "package": null,
  "priority": "P2",
  "creator": "yinxm",
  "assignee": "yinxm",
  "createdAt": "2026-05-19",
  "completedAt": "2026-05-20",
  "branch": null,
  "base_branch": "main",
  "worktree_path": null,
  "commit": "b520d73",
  "pr_url": null,
  "subtasks": [],
  "children": [],
  "parent": null,
  "relatedFiles": [],
  "notes": "",
  "meta": {}
}